pyspj/__init__.py
pyspj/config/__init__.py
pyspj/config/meta.py
pyspj/entry/__init__.py
pyspj/entry/cli/__init__.py
pyspj/entry/cli/base.py
pyspj/entry/cli/cli.py
pyspj/entry/cli/entry.py
pyspj/entry/cli/exception.py
pyspj/entry/cli/values.py
pyspj/entry/script/__init__.py
pyspj/entry/script/decorator.py
pyspj/entry/script/execute.py
pyspj/entry/script/imports.py
pyspj/models/__init__.py
pyspj/models/base.py
pyspj/models/continuity.py
pyspj/models/general.py
pyspj/models/simple.py
pyspj/utils/__init__.py
pyspj/utils/envs.py
pyspj-0.1.0.dist-info/LICENSE
pyspj-0.1.0.dist-info/METADATA
pyspj-0.1.0.dist-info/WHEEL
pyspj-0.1.0.dist-info/entry_points.txt
pyspj-0.1.0.dist-info/top_level.txt
pyspj-0.1.0.dist-info/RECORD
